myapp/__init__.py
myapp/myapp.py
sujayapp/__init__.py
sujayapp/sujayapp.py
sujayapp-1.0.0.dist-info/LICENSE
sujayapp-1.0.0.dist-info/METADATA
sujayapp-1.0.0.dist-info/WHEEL
sujayapp-1.0.0.dist-info/entry_points.txt
sujayapp-1.0.0.dist-info/top_level.txt
sujayapp-1.0.0.dist-info/RECORD
