Metadata-Version: 2.1
Name: sujayapp
Version: 1.0.0
Summary: Demo Package for GfG Article.
Home-page: https://github.com/sujay2002/
Author: Sujay Kanungo
Author-email: sujay2002@gmail.com
License: MIT
Keywords: geeksforgeeks gfg article python package vibhu4agarwal
Platform: UNKNOWN
Classifier: Programming Language :: Python :: 3
Classifier: License :: OSI Approved :: MIT License
Classifier: Operating System :: OS Independent
Requires-Dist: marbaloo-schedule
